cyberninja/__init__.py
cyberninja/__main__.py
cyberninja/cyberninja.py
cyberninja/notify.py
cyberninja/removed_sites.json
cyberninja/result.py
cyberninja/setup.py
cyberninja/site_list.py
cyberninja/sites.py
cyberninja/Cyber-Ninja/__init__.py
cyberninja/Cyber-Ninja/__main__.py
cyberninja/Cyber-Ninja/cyberninja.py
cyberninja/Cyber-Ninja/notify.py
cyberninja/Cyber-Ninja/result.py
cyberninja/Cyber-Ninja/sites.py
cyberninja/Cyber-Ninja/tests/__init__.py
cyberninja/Cyber-Ninja/tests/all.py
cyberninja/Cyber-Ninja/tests/base.py
cyberninja/resources/data.json
cyberninja/tests/__init__.py
cyberninja/tests/all.py
cyberninja/tests/base.py
cyberninja-1.0.0.dist-info/LICENSE
cyberninja-1.0.0.dist-info/METADATA
cyberninja-1.0.0.dist-info/WHEEL
cyberninja-1.0.0.dist-info/entry_points.txt
cyberninja-1.0.0.dist-info/top_level.txt
cyberninja-1.0.0.dist-info/RECORD
