Metadata-Version: 2.2
Name: cyberninja
Version: 1.0.0
Summary: Advanced Social Media Intelligence Tool for username reconnaissance
Home-page: https://github.com/Vimal007Vimal/CyberNinja
Author: Vimal
Author-email: 2004.vimald@gmail.com
Project-URL: Bug Tracker, https://github.com/Vimal007Vimal/CyberNinja/issues
Project-URL: Documentation, https://github.com/Vimal007Vimal/CyberNinja/blob/main/README.md
Keywords: osint,security,social-media,username,reconnaissance,cybersecurity
Classifier: Development Status :: 5 - Production/Stable
Classifier: Intended Audience :: Information Technology
Classifier: Topic :: Security
Classifier: Programming Language :: Python :: 3
Classifier: Programming Language :: Python :: 3.6
Classifier: Programming Language :: Python :: 3.7
Classifier: Programming Language :: Python :: 3.8
Classifier: Programming Language :: Python :: 3.9
Classifier: Programming Language :: Python :: 3.10
Classifier: Programming Language :: Python :: 3.11
Classifier: License :: OSI Approved :: MIT License
Classifier: Operating System :: OS Independent
Requires-Python: >=3.6
License-File: LICENSE
Requires-Dist: beautifulsoup4>=4.9.3
Requires-Dist: bs4
Requires-Dist: certifi
Requires-Dist: colorama
Requires-Dist: lxml
Requires-Dist: PySocks
Requires-Dist: requests>=2.25.1
Requires-Dist: requests-futures>=1.0.0
Requires-Dist: soupsieve
Requires-Dist: stem>=1.8.0
Requires-Dist: torrequest>=0.1.0
Requires-Dist: pyfiglet>=0.8.post1
Requires-Dist: term_image>=0.7.2
Requires-Dist: timg>=1.1.6
Requires-Dist: pillow<11,>=9.1
Dynamic: author
Dynamic: author-email
Dynamic: classifier
Dynamic: description
Dynamic: description-content-type
Dynamic: home-page
Dynamic: keywords
Dynamic: project-url
Dynamic: requires-dist
Dynamic: requires-python
Dynamic: summary
